rustenv.py
rustenv-0.0.6.dist-info/LICENSE
rustenv-0.0.6.dist-info/METADATA
rustenv-0.0.6.dist-info/WHEEL
rustenv-0.0.6.dist-info/entry_points.txt
rustenv-0.0.6.dist-info/top_level.txt
rustenv-0.0.6.dist-info/RECORD
