Metadata-Version: 2.1
Name: rustenv
Version: 0.0.6
Summary: Virtual, activate-able environments for Rust
Home-page: https://github.com/chriskuehl/rustenv
Author: Chris Kuehl
Author-email: ckuehl@ckuehl.me
Classifier: License :: OSI Approved :: Apache Software License
Classifier: Programming Language :: Python :: 3
Classifier: Programming Language :: Python :: 3 :: Only
Classifier: Programming Language :: Python :: Implementation :: CPython
Classifier: Programming Language :: Python :: Implementation :: PyPy
Requires-Python: >=3.7
License-File: LICENSE
